odoo10_addon_connector_lengow-10.0.1.0.2-py2.7-nspkg.pth
odoo/addons/connector_lengow/README.rst
odoo/addons/connector_lengow/__init__.py
odoo/addons/connector_lengow/__manifest__.py
odoo/addons/connector_lengow/components/__init__.py
odoo/addons/connector_lengow/components/adapter.py
odoo/addons/connector_lengow/components/binder.py
odoo/addons/connector_lengow/components/core.py
odoo/addons/connector_lengow/components/exporter.py
odoo/addons/connector_lengow/components/importer.py
odoo/addons/connector_lengow/components/mapper.py
odoo/addons/connector_lengow/data/lengow_data.xml
odoo/addons/connector_lengow/models/__init__.py
odoo/addons/connector_lengow/models/account_payment_mode.py
odoo/addons/connector_lengow/models/configurator.py
odoo/addons/connector_lengow/models/connector.py
odoo/addons/connector_lengow/models/delivery.py
odoo/addons/connector_lengow/models/lengow_model.py
odoo/addons/connector_lengow/models/product.py
odoo/addons/connector_lengow/models/res_partner.py
odoo/addons/connector_lengow/models/sale.py
odoo/addons/connector_lengow/models/stock.py
odoo/addons/connector_lengow/security/ir.model.access.csv
odoo/addons/connector_lengow/security/security.xml
odoo/addons/connector_lengow/tests/__init__.py
odoo/addons/connector_lengow/tests/common.py
odoo/addons/connector_lengow/tests/test_lengow_discount_wizard.py
odoo/addons/connector_lengow/tests/test_lengow_model.py
odoo/addons/connector_lengow/tests/test_lengow_product_binding_wizard.py
odoo/addons/connector_lengow/tests/test_lengow_product_export.py
odoo/addons/connector_lengow/tests/test_lengow_sale.py
odoo/addons/connector_lengow/tests/test_lengow_stock.py
odoo/addons/connector_lengow/views/account_payment_mode_view.xml
odoo/addons/connector_lengow/views/delivery_view.xml
odoo/addons/connector_lengow/views/lengow_menu.xml
odoo/addons/connector_lengow/views/lengow_model_view.xml
odoo/addons/connector_lengow/views/product_view.xml
odoo10_addon_connector_lengow-10.0.1.0.2.dist-info/DESCRIPTION.rst
odoo10_addon_connector_lengow-10.0.1.0.2.dist-info/METADATA
odoo10_addon_connector_lengow-10.0.1.0.2.dist-info/RECORD
odoo10_addon_connector_lengow-10.0.1.0.2.dist-info/WHEEL
odoo10_addon_connector_lengow-10.0.1.0.2.dist-info/metadata.json
odoo10_addon_connector_lengow-10.0.1.0.2.dist-info/namespace_packages.txt
odoo10_addon_connector_lengow-10.0.1.0.2.dist-info/top_level.txt
