Metadata-Version: 2.0
Name: odoo10-addon-connector-lengow
Version: 10.0.1.0.2
Summary: Module used to connect Odoo to Lengow
Home-page: https://odoo-community.org/
Author: Cédric Pigeon, ACSONE SA/NV, Odoo Community Association (OCA)
Author-email: support@odoo-community.org
License: AGPL-3
Platform: UNKNOWN
Classifier: Programming Language :: Python
Classifier: Framework :: Odoo
Classifier: License :: OSI Approved :: GNU Affero General Public License v3
Requires-Python: ~=2.7
Requires-Dist: ftputil
Requires-Dist: odoo (<10.1dev,>=10.0)
Requires-Dist: odoo10-addon-connector-ecommerce
Requires-Dist: odoo10-addon-product-sequence
Requires-Dist: odoo10-addon-product-state
